superpixel_labeling_tool/__init__.py
superpixel_labeling_tool/cli.py
superpixel_labeling_tool/gui.py
superpixel_labeling_tool/segmentation.py
superpixel_labeling_tool-0.1.1.dist-info/licenses/LICENSE
superpixel_labeling_tool-0.1.1.dist-info/METADATA
superpixel_labeling_tool-0.1.1.dist-info/WHEEL
superpixel_labeling_tool-0.1.1.dist-info/entry_points.txt
superpixel_labeling_tool-0.1.1.dist-info/top_level.txt
superpixel_labeling_tool-0.1.1.dist-info/RECORD
