Metadata-Version: 2.4
Name: superpixel_labeling_tool
Version: 0.1.1
Summary: Tool for superpixel-based annotation and segmentation mask generation.
Author-email: Marc Adrian Peters <marcadrianpeters@gmail.com>
License:                     GNU GENERAL PUBLIC LICENSE
Requires-Python: >=3.8
License-File: LICENSE
Requires-Dist: opencv-python
Requires-Dist: numpy
Requires-Dist: tqdm
Requires-Dist: scikit-image
Requires-Dist: pillow
Requires-Dist: scipy
Requires-Dist: pyqt6
Provides-Extra: dev
Requires-Dist: jupyterlab; extra == "dev"
Requires-Dist: ipykernel; extra == "dev"
Dynamic: license-file
